pydiceplot/__init__.py
pydiceplot/_backend.py
pydiceplot/plots/__init__.py
pydiceplot/plots/_plot.py
pydiceplot/plots/backends/__init__.py
pydiceplot/plots/backends/_dice_utils.py
pydiceplot/plots/backends/_domino_utils.py
pydiceplot/plots/backends/_matplotlib_backend.py
pydiceplot/plots/backends/_plotly_backend.py
pydiceplot-0.0.3.dist-info/LICENSE
pydiceplot-0.0.3.dist-info/METADATA
pydiceplot-0.0.3.dist-info/WHEEL
pydiceplot-0.0.3.dist-info/top_level.txt
pydiceplot-0.0.3.dist-info/RECORD
